data_cleaning_assistant/__init__.py
data_cleaning_assistant/data_cleaning_assistant.py
data_cleaning_assistant/reporting.py
data_cleaning_assistant/utils.py
data_cleaning_assistant/visualization.py
test/__init__.py
test/test_data_cleaning_assistant.py
data_cleaning_assistant-0.1.0.dist-info/LICENSE
data_cleaning_assistant-0.1.0.dist-info/METADATA
data_cleaning_assistant-0.1.0.dist-info/WHEEL
data_cleaning_assistant-0.1.0.dist-info/top_level.txt
data_cleaning_assistant-0.1.0.dist-info/RECORD
